eric_api.py
eric_api-1.6.0.8.dist-info/LICENSE
eric_api-1.6.0.8.dist-info/METADATA
eric_api-1.6.0.8.dist-info/WHEEL
eric_api-1.6.0.8.dist-info/RECORD
