Metadata-Version: 2.3
Name: eric-api
Version: 1.6.0.8
Summary: A Server sent events based messaging microservice implementation
License: MIT
Keywords: sse,api,rest,server sent events,microservice,messaging
Author: Luca Stretti
Author-email: laxertu@gmail.com
Requires-Python: >=3.10,<3.12
Classifier: License :: OSI Approved :: MIT License
Classifier: Programming Language :: Python :: 3
Classifier: Programming Language :: Python :: 3.10
Classifier: Programming Language :: Python :: 3.11
Requires-Dist: dotenv (>=0.9.9,<0.10.0)
Requires-Dist: eric-redis-queues (==2.0.0.10)
Requires-Dist: fastapi (>=0.115.12,<0.116.0)
Requires-Dist: requests (>=2.32.4,<3.0.0)
Requires-Dist: sse-starlette (>=2.2.1,<3.0.0)
Requires-Dist: sseclient (>=0.0.27,<0.0.28)
Requires-Dist: uvicorn (>=0.34.1,<0.35.0)
Project-URL: Issues, https://github.com/laxertu/eric-api/issues
Project-URL: Repository, https://github.com/laxertu/eric-api
